odoo/addons/invader_payment/README.rst
odoo/addons/invader_payment/__init__.py
odoo/addons/invader_payment/__manifest__.py
odoo/addons/invader_payment/models/__init__.py
odoo/addons/invader_payment/models/account_payment_mode.py
odoo/addons/invader_payment/models/invader_payable.py
odoo/addons/invader_payment/models/payment_transaction.py
odoo/addons/invader_payment/readme/CONTRIBUTORS.rst
odoo/addons/invader_payment/readme/DESCRIPTION.rst
odoo/addons/invader_payment/services/__init__.py
odoo/addons/invader_payment/services/invader_payment_service.py
odoo/addons/invader_payment/static/description/index.html
odoo/addons/invader_payment/views/account_payment_mode.xml
odoo12_addon_invader_payment-12.0.2.0.0.dist-info/METADATA
odoo12_addon_invader_payment-12.0.2.0.0.dist-info/WHEEL
odoo12_addon_invader_payment-12.0.2.0.0.dist-info/top_level.txt
odoo12_addon_invader_payment-12.0.2.0.0.dist-info/RECORD
